Workbook

Sheet Sanitized
A1: sale_id | B1: SaleDateSanitized | C1: customer_name | D1: PorscheModelSanitized | E1: ModelYearSanitized | F1: SalesPriceSanitized | G1: VehicleMileageSanitized | H1: PayMethodSanitized | I1: CitySanitized | J1: StateSanitized | K1: salesperson | L1: DeliveryStatusSanitized
A2: 6 | B2: 2024-02-30 | C2: Michael Adams | D2: 718 Cayman | E2: 2022 | F2: 79500.00 | G2: 9800 | H2: Credit Card | I2: =VLOOKUP(#REF!,Normalize.db!H:I,2,FALSE) -> #REF! | J2: MA | K2: kevin | L2: =VLOOKUP(#REF!,Normalize.db!B:C,2,FALSE) -> #REF!
A3: 7 | B3: 2024-03-14 | C3: SOPHIA Miller | D3: 911 Turbo S | E3: 2024 | F3: 235000.00 | G3: 1200 | H3: Wire Transfer | I3: =VLOOKUP(#REF!,Normalize.db!H:I,2,FALSE) -> #REF! | J3: WA | K3: AMANDA scott | L3: =VLOOKUP(#REF!,Normalize.db!B:C,2,FALSE) -> #REF!
A4: 8 | B4: 2024-04-18 | C4: Daniel-Jones | D4: Cayenne Coupe | E4: 2023 | F4: 112750.00 | G4: 6400 | H4: Financing | I4: =VLOOKUP(#REF!,Normalize.db!H:I,2,FALSE) -> #REF! | J4: TX | K4: Brian Hall | L4: =VLOOKUP(#REF!,Normalize.db!B:C,2,FALSE) -> #REF!
A5: 9 | B5: INVALID | C5: Olivia Brown | D5: Macan S | E5: 2021 | F5: 68900.00 | G5: 28 | H5: Cash | I5: =VLOOKUP(#REF!,Normalize.db!H:I,2,FALSE) -> #REF! | J5: CO | K5: jessica | L5: =VLOOKUP(#REF!,Normalize.db!B:C,2,FALSE) -> #REF!
A6: 10 | B6: 2024-05-22 | C6: Ethan Wilson | D6: Taycan 4S | E6: 2024 | F6: 121000.00 | G6: 0 | H6: Bank Transfer | I6: =VLOOKUP(#REF!,Normalize.db!H:I,2,FALSE) -> #REF! | J6: CA | K6: Thomas King | L6: =VLOOKUP(#REF!,Normalize.db!B:C,2,FALSE) -> #REF!
A7: 11 | B7: 2024-08-06 | C7: Ava Martinez | D7: Panamera 4 | E7: 2023 | F7: 104500.00 | G7: 14500 | H7: Credit Card | I7: =VLOOKUP(#REF!,Normalize.db!H:I,2,FALSE) -> #REF! | J7: FL | K7: LISA ray | L7: =VLOOKUP(#REF!,Normalize.db!B:C,2,FALSE) -> #REF!
A8: 12 | B8: 2024-07-11 | C8: Noah Davis | D8: 911 Carrera S | E8: 2020 | F8: 96300.00 | G8: 41000 | H8: Lease | I8: =VLOOKUP(#REF!,Normalize.db!H:I,2,FALSE) -> #REF! | J8: NY | K8: Mark Evans | L8: =VLOOKUP(#REF!,Normalize.db!B:C,2,FALSE) -> #REF!
A9: 13 | B9: INVALID | C9: Isabella Garcia | D9: Cayenne E-Hybrid | E9: 2022 | F9: 89750.00 | G9: 11744 | H9: Wire Transfer | I9: =VLOOKUP(#REF!,Normalize.db!H:I,2,FALSE) -> #REF! | J9: CA | K9: nancy reed | L9: =VLOOKUP(#REF!,Normalize.db!B:C,2,FALSE) -> #REF!
A10: 14 | B10: 2024-08-19 | C10: Liam Rodriguez | D10: 718 Boxster | E10: 2021 | F10: 73500.00 | G10: 22300 | H10: Debit Card | I10: =VLOOKUP(#REF!,Normalize.db!H:I,2,FALSE) -> #REF! | J10: IL | K10: George Bell | L10: =VLOOKUP(#REF!,Normalize.db!B:C,2,FALSE) -> #REF!
A11: 15 | B11: 2024-09-02 | C11: Mia Hernandez | D11: Macan GTS | E11: 2024 | F11: 95000.00 | G11: 3500 | H11: Financing | I11: =VLOOKUP(#REF!,Normalize.db!H:I,2,FALSE) -> #REF! | J11: AZ | K11: Helen Brooks | L11: =VLOOKUP(#REF!,Normalize.db!B:C,2,FALSE) -> #REF!
A12: 16 | B12: 2024-09-17 | C12: James Lopez | D12: Taycan Turbo | E12: 2023 | F12: 153200.50 | G12: 11 | H12: ACH Payment | I12: =VLOOKUP(#REF!,Normalize.db!H:I,2,FALSE) -> #REF! | J12: TX | K12: samuel price | L12: =VLOOKUP(#REF!,Normalize.db!B:C,2,FALSE) -> #REF!
A13: 17 | B13: INVALID | C13: Charlotte Young | D13: 911 GT3 | E13: 2024 | F13: 241000.00 | G13: 750 | H13: Wire Transfer | I13: =VLOOKUP(#REF!,Normalize.db!H:I,2,FALSE) -> #REF! | J13: NV | K13: PETER Ford | L13: =VLOOKUP(#REF!,Normalize.db!B:C,2,FALSE) -> #REF!
... A101: 105 | B101: 2027-10-01 | C101: Madison Powell | D101: 911 Dakar | E101: 2024 | F101: 271700.00 | G101: 1050 | H101: Lease | I101: =VLOOKUP(#REF!,Normalize.db!H:I,2,FALSE) -> #REF! | J101: LA | K101: Steve Ross | L101: =VLOOKUP(#REF!,Normalize.db!B:C,2,FALSE) -> #REF!

Sheet Normalize.db
B1: delivery_status | C1: DeliveryStatusSanitized | H1: city | I1: CitySanitized | K1: payment_method | L1: PayMethodSanitized
B2: delivered | C2: Delivered | H2: boston | I2: Boston | K2: Credit card | L2: Credit Card
B3: DELIVERED | C3: Delivered | H3: Seattle | I3: Seattle | K3: wire transfer | L3: Wire Transfer
B4: in Transit | C4: In Transit | H4: austin | I4: Austin | K4: Financing plan | L4: Financing
B5: Pending | C5: Pending | H5: Denver | I5: Denver | K5: CASH | L5: Cash
B6: delivered!!! | C6: Delivered | H6: los angeles | I6: Los Angeles | K6: bank-transfer | L6: Bank Transfer
B7: cancelled | C7: Cancelled | H7: Miami | I7: Miami | K7: Credit Card | L7: Credit Card
B8: DELIVERD | C8: Delivered | H8: new york | I8: New York | K8: lease | L8: Lease
B9: pending approval | C9: Pending Approval | H9: San Diego | I9: San Diego | K9: bank wire | L9: Wire Transfer
B10: shipped | C10: Shipped | H10: chicago | I10: Chicago | K10: debit card | L10: Debit Card
B11: IN TRANSIT | C11: In Transit | H11: phoenix | I11: Phoenix | K11: Financing | L11: Financing
B12: delivered | C12: Delivered | H12: dallas | I12: Dallas | K12: ACH payment | L12: ACH Payment
... B101: Delivered | C101: Delivered | H101: new orleans | I101: New Orleans | K101: Leasing | L101: Lease
